DWLX/__init__.py
DWLX/dwlx.py
dwlx-0.2.3.dist-info/licenses/LICENSE
dwlx-0.2.3.dist-info/WHEEL
dwlx-0.2.3.dist-info/METADATA
dwlx-0.2.3.dist-info/RECORD
