Metadata-Version: 2.4
Name: DWLX
Version: 0.2.3
Summary: Initialize python tools to avoid platform errors
Author-email: Guillaume <guillaume.plagier@example.com>
License-File: LICENSE
Requires-Dist: requests
